codenitro/__init__.py
codenitro/config.py
codenitro/nitro.py
codenitro/painter.py
codenitro-1.1.1.dist-info/LICENSE
codenitro-1.1.1.dist-info/METADATA
codenitro-1.1.1.dist-info/WHEEL
codenitro-1.1.1.dist-info/entry_points.txt
codenitro-1.1.1.dist-info/top_level.txt
codenitro-1.1.1.dist-info/RECORD
