Metadata-Version: 2.1
Name: codenitro
Version: 1.1.1
Summary: Code to image from the command line
Author-email: Luke Salamone <lukesalamone94@gmail.com>
Project-URL: Homepage, https://github.com/lukesalamone/code_nitro
Project-URL: Bug Tracker, https://github.com/lukesalamone/code_nitro/issues
Classifier: Development Status :: 5 - Production/Stable
Classifier: Environment :: Console
Classifier: Intended Audience :: Developers
Classifier: License :: OSI Approved :: MIT License
Classifier: Programming Language :: Python :: 3
Classifier: Programming Language :: Python :: 3.7
Classifier: Topic :: Software Development
Classifier: Topic :: Software Development :: Documentation
Classifier: Topic :: Utilities
Requires-Python: >=3.7
License-File: LICENSE
Requires-Dist: Pillow>=10.0.0
Requires-Dist: Pygments>=2.15.1
Requires-Dist: requests>=2.31.0
